ABitOfLove/__init__.py
ABitOfLove/foryou.py
abitoflove-0.2.2.dist-info/METADATA
abitoflove-0.2.2.dist-info/WHEEL
abitoflove-0.2.2.dist-info/entry_points.txt
abitoflove-0.2.2.dist-info/top_level.txt
abitoflove-0.2.2.dist-info/RECORD
